{
  "$schema": "https://schemas.wp.org/trunk/block.json",
  "apiVersion": 2,
  "name": "create-block/faculty-member-landing",
  "parent": [
    "create-block/faculty-landing"
  ],
  "version": "0.1.0",
  "title": "Faculty Member",
  "category": "theme",
  "icon": "index-card",
  "description": "",
  "supports": {
    "html": false
  },
  "attributes": {
    "name": {
      "type": "string",
      "default": ""
    },
    "title": {
      "type": "string",
      "default": ""
    },
    "phone": {
      "type": "string",
      "default": ""
    },
    "email": {
      "type": "string",
      "default": ""
    },
    "bioLink": {
      "type": "string",
      "default": ""
    },
    "hasLinkNofollow": {
      "type": "boolean",
      "default": false
    },
    "openNewTab": {
      "type": "boolean",
      "default": false
    },
    "mediaID": {
      "type": "number",
      "default": ""
    },
    "mediaURL": {
      "type": "string",
      "default": ""
    }
  },
  "textdomain": "faculty-member-landing",
  "editorScript": "file:./index.js",
  "editorStyle": "file:./index.css",
  "style": "file:./style-index.css"
}